picireny/__init__.py
picireny/__main__.py
picireny/cli.py
picireny/filter.py
picireny/hdd.py
picireny/hdd_tree.py
picireny/hddr.py
picireny/hoist.py
picireny/info.py
picireny/prune.py
picireny/transform.py
picireny/antlr4/__init__.py
picireny/antlr4/antlr_tree.py
picireny/antlr4/grammar_analyzer.py
picireny/antlr4/hdd_tree_builder.py
picireny/antlr4/parser_builder.py
picireny/antlr4/parser/ANTLRv4Lexer.py
picireny/antlr4/parser/ANTLRv4Parser.py
picireny/antlr4/parser/LexerAdaptor.py
picireny/antlr4/parser/__init__.py
picireny/antlr4/resources/ANTLRv4Lexer.g4
picireny/antlr4/resources/ANTLRv4Parser.g4
picireny/antlr4/resources/ExtendedTargetParser.java
picireny/antlr4/resources/LexBasic.g4
picireny/srcml/__init__.py
picireny/srcml/hdd_tree_builder.py
picireny-21.8.dist-info/LICENSE.rst
picireny-21.8.dist-info/METADATA
picireny-21.8.dist-info/WHEEL
picireny-21.8.dist-info/entry_points.txt
picireny-21.8.dist-info/top_level.txt
picireny-21.8.dist-info/RECORD
