Metadata-Version: 2.1
Name: picireny
Version: 21.8
Summary: Picireny Hierarchical Delta Debugging Framework
Home-page: https://github.com/renatahodovan/picireny
Author: Renata Hodovan, Akos Kiss
Author-email: hodovan@inf.u-szeged.hu, akiss@inf.u-szeged.hu
License: BSD
Platform: any
Classifier: Intended Audience :: Developers
Classifier: License :: OSI Approved :: BSD License
Classifier: Operating System :: OS Independent
Classifier: Programming Language :: Python
Classifier: Programming Language :: Python :: 3
Classifier: Programming Language :: Python :: 3.5
Classifier: Programming Language :: Python :: 3.6
Classifier: Programming Language :: Python :: 3.7
Classifier: Programming Language :: Python :: 3.8
Classifier: Programming Language :: Python :: 3.9
Classifier: Topic :: Software Development :: Testing
Requires-Python: >=3.5
License-File: LICENSE.rst
Requires-Dist: antlerinator (>=1!1.0.0)
Requires-Dist: antlr4-python3-runtime (==4.9.2)
Requires-Dist: inators
Requires-Dist: picire (==21.8)
Requires-Dist: importlib-metadata ; python_version < "3.8"
